linqs_pacai-1.4.1.dist-info/licenses/LICENSE.md
pacai/__init__.py
linqs_pacai-1.4.1.dist-info/METADATA
linqs_pacai-1.4.1.dist-info/WHEEL
linqs_pacai-1.4.1.dist-info/top_level.txt
linqs_pacai-1.4.1.dist-info/RECORD
