Metadata-Version: 2.4
Name: linqs-pacai
Version: 1.4.1
Summary: A modified version of the Pacman educational project from the Berkley AI Lab. (Moved to edq-pacai.)
Author-email: Eriq Augustine <eaugusti@ucsc.edu>, LINQS <linqs.edu@gmail.com>
License: ## Pacman
Project-URL: Homepage, https://github.com/edulinq/pacai
Project-URL: Repository, https://github.com/edulinq/pacai
Keywords: AI,Artificial Intelligence,Education,Teaching
Classifier: Intended Audience :: Science/Research
Classifier: Intended Audience :: Education
Classifier: Operating System :: OS Independent
Classifier: Programming Language :: Python :: 3.8
Classifier: Topic :: Education
Classifier: Topic :: Scientific/Engineering :: Artificial Intelligence
Requires-Python: >=3.8
License-File: LICENSE.md
Requires-Dist: edq-pacai
Dynamic: license-file
